<?xml version="1.0" ?>
<odoo>
    <data>

        <record id="viafirma_biometric_signature" model="viafirma.signature">
            <field name="type">signature</field>
            <field name="name">BIOMETRIC</field>
            <field name="value">email</field>
        </record>

        <!--<record id="viafirma_mobile_signature" model="viafirma.signature">
            <field name="type">signature</field>
            <field name="name">MOBILE</field>
            <field name="value">mobile</field>
        </record>

        <record id="viafirma_certificate_signature" model="viafirma.signature">
            <field name="type">signature</field>
            <field name="name">CERTIFICATE</field>
            <field name="value">certificate</field>
        </record>-->

        <record id="viafirma_mail_notification" model="viafirma.notification">
            <field name="type">notification</field>
            <field name="name">MAIL</field>
            <field name="value">email</field>
        </record>

       <!--<record id="viafirma_mobile_notification" model="viafirma.notification">
            <field name="type">notification</field>
            <field name="name">SMS</field>
            <field name="value">mobile</field>
        </record>-->

        <!--<record id="viafirma_mail_mobile_notification" model="viafirma.notification">
            <field name="type">notification</field>
            <field name="name">MAIL_SMS</field>
            <field name="value">mail_sms</field>
        </record>-->

    </data>
</odoo>
